README.md
setup.cfg
setup.py
src/descriptor_tools/__init__.py
src/descriptor_tools/decorators.py
src/descriptor_tools/desc_dict.py
src/descriptor_tools/find_descriptors.py
src/descriptor_tools/mixins.py
src/descriptor_tools/names.py
src/descriptor_tools/properties.py
src/descriptor_tools/set_attrs.py
src/descriptor_tools/storage.py
src/descriptor_tools/unboundattr.py
src/descriptor_tools.egg-info/PKG-INFO
src/descriptor_tools.egg-info/SOURCES.txt
src/descriptor_tools.egg-info/dependency_links.txt
src/descriptor_tools.egg-info/top_level.txt
src/descriptor_tools/instance_properties/__init__.py
src/descriptor_tools/instance_properties/built_ins.py
src/descriptor_tools/instance_properties/core.py