Metadata-Version: 1.1
Name: descriptor-tools
Version: 1.1.0
Summary: A collection of classes and functions to make the creation of descriptors simpler and quicker
Home-page: https://github.com/sad2project/descriptor-tools
Author: Jacob Zimmerman
Author-email: sad2project@gmail.com
License: CC0 1.0 Universal
Download-URL: https://github.com/sad2project/descriptor-tools/tarball/1.1.0
Keywords: descriptors,properties
Platform: UNKNOWN
Classifier: Development Status :: 5 - Production/Stable
Classifier: Intended Audience :: Developers
Classifier: Natural Language :: English
Classifier: Operating System :: OS Independent
Classifier: License :: CC0 1.0 Universal (CC0 1.0) Public Domain Dedication
Classifier: Programming Language :: Python
Classifier: Programming Language :: Python :: 3.3
Classifier: Programming Language :: Python :: 3.4
Classifier: Programming Language :: Python :: 3.5
Classifier: Programming Language :: Python :: 3.6
Classifier: Programming Language :: Python :: 3.7
Classifier: Programming Language :: Python :: Implementation :: CPython
Classifier: Programming Language :: Python :: Implementation :: PyPy
Classifier: Topic :: Software Development :: Libraries :: Python Modules
